RMC/__init__.py
RMC/costfunctions/__init__.py
RMC/costfunctions/finalCosts.py
RMC/costfunctions/runningCosts.py
RMC/design/__init__.py
RMC/design/generate_design.py
RMC/emulator/GP.py
RMC/emulator/__init__.py
RMC/model/__init__.py
RMC/model/hybridcontrol.py
RMC/model/hybridrunner.py
RMC/model/test_inputs.py
RMC/optimization/__init__.py
RMC/optimization/onestepOptimization.py
RMC/simulate/CIR.py
RMC/simulate/OU.py
RMC/simulate/__init__.py
RMC/simulate/jacobi.py
RMC/simulate/sim.py
RMCgp-0.0.30.dist-info/LICENSE.txt
RMCgp-0.0.30.dist-info/METADATA
RMCgp-0.0.30.dist-info/WHEEL
RMCgp-0.0.30.dist-info/top_level.txt
RMCgp-0.0.30.dist-info/RECORD
