Metadata-Version: 2.1
Name: RMCgp
Version: 0.0.30
Summary: RMC for stochastic control.
Home-page: https://github.com/thihaa2019/RMCgp
Author: Thiha Aung
Author-email: taung@ucsb.edu
Maintainer: Thiha Aung
Maintainer-email: taung@ucsb.edu
License: Apache-2.0
Classifier: Programming Language :: Python :: 3
Classifier: License :: OSI Approved :: Apache Software License
Requires-Python: >=3.9
License-File: LICENSE.txt
Requires-Dist: numpy ==1.24.3
Requires-Dist: six
Requires-Dist: paramz ==0.9.5
Requires-Dist: cython >=0.29
Requires-Dist: GPy ==1.10.0
Requires-Dist: scikit-learn ==1.3.0
Requires-Dist: scipy ==1.11.4
Requires-Dist: matplotlib ==3.7.1
Requires-Dist: python ==3.10.12
Provides-Extra: dev
Requires-Dist: pytest >=7.0 ; extra == 'dev'
Requires-Dist: twine >=4.0.2 ; extra == 'dev'
